setup.cfg
setup.py
rlog/__init__.py
rlog/_compat.py
rlog/formatters.py
rlog/handlers.py
rlog.egg-info/PKG-INFO
rlog.egg-info/SOURCES.txt
rlog.egg-info/dependency_links.txt
rlog.egg-info/requires.txt
rlog.egg-info/top_level.txt
tests/__init__.py
tests/_compat.py
tests/conftest.py
tests/test_formatters.py
tests/test_handlers.py