Metadata-Version: 1.1
Name: rlog
Version: 0.3
Summary: Small handler and formatter for using python logging with Redis
Home-page: https://github.com/lobziik/rlog
Author: lobziik
Author-email: lobziiko.o@gmail.com
License: MIT
Keywords: Redis,logging,log,logs
Platform: UNKNOWN
Classifier: Development Status :: 5 - Production/Stable
Classifier: Environment :: Console
Classifier: Intended Audience :: Developers
Classifier: License :: OSI Approved :: MIT License
Classifier: Operating System :: OS Independent
Classifier: Programming Language :: Python
Classifier: Programming Language :: Python :: 2.6
Classifier: Programming Language :: Python :: 2.7
Classifier: Programming Language :: Python :: 3
Classifier: Programming Language :: Python :: 3.5
Classifier: Programming Language :: Python :: 3.6
Classifier: Programming Language :: Python :: Implementation :: CPython
Classifier: Programming Language :: Python :: Implementation :: PyPy
